sqlalchemy_ibmi/__init__.py
sqlalchemy_ibmi/base.py
sqlalchemy_ibmi/constants.py
sqlalchemy_ibmi/requirements.py
crazy_ibmi-0.10.0.dist-info/entry_points.txt
crazy_ibmi-0.10.0.dist-info/LICENSE
crazy_ibmi-0.10.0.dist-info/WHEEL
crazy_ibmi-0.10.0.dist-info/METADATA
crazy_ibmi-0.10.0.dist-info/RECORD
